{
    "world": "E",
    "subworld": 5,
    "panel": 1,
    "page": 4,
    "enemy_context": ["carriers", "subs"],
    "nodes": {
        "A": {
            "coords": [857, 358]
        },
        "B": {
            "coords": [769, 384]
        },
        "C": {
            "coords": [697, 355],
            "types": ["air"]
        },
        "D": {
            "coords": [599, 287],
            "types": ["sub"]
        },
        "E": {
            "coords": [461, 306]
        },
        "F": {
            "coords": [318, 326]
        },
        "F1": {
            "coords": [333, 246],
            "types": ["sub"]
        },
        "F2": {
            "coords": [299, 408],
            "types": ["air"]
        },
        "G": {
            "coords": [181, 356],
            "types": ["boss"]
        },
        "H": {
            "coords": [964, 546]
        },
        "I": {
            "coords": [850, 537],
            "types": ["sub"]
        },
        "J": {
            "coords": [711, 500]
        },
        "J1": {
            "coords": [821, 428],
            "types": ["air"]
        },
        "J2": {
            "coords": [642, 549]
        },
        "K": {
            "coords": [564, 469],
            "types": ["air"]
        },
        "L": {
            "coords": [518, 249]
        },
        "M": {
            "coords": [375, 176]
        },
        "M1": {
            "coords": [485, 149],
            "types": ["air"]
        },
        "M2": {
            "coords": [278, 130]
        },
        "N": {
            "coords": [232, 222],
            "types": ["boss"]
        },
        "O": {
            "coords": [465, 437]
        },
        "P": {
            "coords": [565, 544]
        },
        "Q": {
            "coords": [664, 406]
        },
        "Q1": {
            "coords": [606, 415],
            "types": ["sub"]
        },
        "Q2": {
            "coords": [629, 451],
            "types": ["sub"]
        },
        "R": {
            "coords": [740, 297],
            "types": ["select"]
        },
        "S": {
            "coords": [668, 243],
            "types": ["select"]
        },
        "S1": {
            "coords": [703, 204],
            "types": ["sub"]
        },
        "S2": {
            "coords": [729, 167],
            "types": ["air"]
        },
        "T": {
            "coords": [588, 183]
        },
        "U": {
            "coords": [824, 149],
            "types": ["sub"]
        },
        "V": {
            "coords": [873, 206]
        },
        "W": {
            "coords": [941, 137]
        },
        "X": {
            "coords": [931, 203]
        },
        "Y": {
            "coords": [1028, 204],
            "types": ["boss"]
        }
    },
    "edges": {
        "1": ["Start 1", "A"],
        "2": ["A", "B"],
        "3": ["B", "C"],
        "4": ["C", "D"],
        "5": ["D", "E"],
        "6": ["E", "F"],
        "7": ["E", "F1"],
        "8": ["F", "F2"],
        "9": ["F2", "F3"],
        "10": ["F", "G"],
        "11": ["F1", "F"],
        "12": ["F2", "G"],
        "13": ["Start 2", "H"],
        "14": ["H", "I"],
        "15": ["I", "J"],
        "16": ["J", "J1"],
        "17": ["J", "J2"],
        "18": ["J", "K"],
        "19": ["K", "L"],
        "20": ["L", "M"],
        "21": ["L", "M1"],
        "22": ["M", "M2"],
        "23": ["M", "N"],
        "24": ["J1", "J"],
        "25": ["J2", "K"],
        "26": ["M1", "M"],
        "28": ["Start 3", "O"],
        "29": ["O", "P"],
        "30": ["Q1", "Q"],
        "31": ["O", "Q1"],
        "32": ["P", "Q2"],
        "33": ["C", "R"],
        "34": ["R", "R1"],
        "35": ["R1", "R2"],
        "36": ["R", "S"],
        "37": ["S", "S1"],
        "38": ["S1", "S2"],
        "39": ["S", "T"],
        "40": ["Q2", "Q"],
        "41": ["Q", "C"],
        "43": ["S2", "U"],
        "44": ["U", "V"],
        "45": ["U", "W"],
        "46": ["W", "X"],
        "47": ["W", "Y"],
        "48": ["V", "W"],
        "49": ["R1", "Z"],
        "50": ["Start 4", "C"],
        "51": ["Start 4", "R"],
        "52": ["R1", "S2"],
        "53": ["Z", "U"]
    }
}
